[
	{
		"time": 1547894164,
		"latitude": 46.75115,
		"longitude": 23.577837,
		"altitude": 472.4,
		"speed": 0.01,
		"timelocal": 120,
		"temperature": -3.47,
		"pressure": 96770,
		"humidity": 88.64,
		"voc": 43127,
		"co2": 683,
		"ch2o": null,
		"pm25": null,
		"cpm": 8,
		"voltage": 380,
		"duty": 170
	},
	{
		"time": 1547894224,
		"latitude": 46.751157,
		"longitude": 23.577841,
		"altitude": 473.8,
		"speed": 0,
		"timelocal": 180,
		"temperature": -3.19,
		"pressure": 96766,
		"humidity": 88.59,
		"voc": 43161,
		"co2": 682,
		"ch2o": null,
		"pm25": null,
		"cpm": 5,
		"voltage": 377,
		"duty": 169
	},
	{
		"time": 1547894284,
		"latitude": 46.751158,
		"longitude": 23.57783,
		"altitude": 474.1,
		"speed": 0.01,
		"timelocal": 240,
		"temperature": -3.01,
		"pressure": 96762,
		"humidity": 88.51,
		"voc": 44834,
		"co2": 678,
		"ch2o": null,
		"pm25": null,
		"cpm": 15,
		"voltage": 378,
		"duty": 168
	},
	{
		"time": 1547894344,
		"latitude": 46.751159,
		"longitude": 23.577825,
		"altitude": 474.2,
		"speed": 0.02,
		"timelocal": 300,
		"temperature": -2.84,
		"pressure": 96760,
		"humidity": 88.46,
		"voc": 47110,
		"co2": 672,
		"ch2o": null,
		"pm25": null,
		"cpm": 10,
		"voltage": 377,
		"duty": 168
	},
	{
		"time": 1547894404,
		"latitude": 46.751151,
		"longitude": 23.577824,
		"altitude": 473.7,
		"speed": 0.02,
		"timelocal": 360,
		"temperature": -2.6900000000000004,
		"pressure": 96758,
		"humidity": 88.42,
		"voc": 49123,
		"co2": 659,
		"ch2o": null,
		"pm25": null,
		"cpm": 5,
		"voltage": 377,
		"duty": 168
	},
	{
		"time": 1547894464,
		"latitude": 46.751145,
		"longitude": 23.577833,
		"altitude": 474.8,
		"speed": 0.01,
		"timelocal": 420,
		"temperature": -2.5599999999999996,
		"pressure": 96755,
		"humidity": 88.37,
		"voc": 50859,
		"co2": 658,
		"ch2o": null,
		"pm25": null,
		"cpm": 9,
		"voltage": 381,
		"duty": 169
	},
	{
		"time": 1547894524,
		"latitude": 46.75115,
		"longitude": 23.577828,
		"altitude": 476,
		"speed": 0.01,
		"timelocal": 480,
		"temperature": -2.4299999999999997,
		"pressure": 96751,
		"humidity": 88.32,
		"voc": 52722,
		"co2": 653,
		"ch2o": null,
		"pm25": null,
		"cpm": 14,
		"voltage": 380,
		"duty": 169
	},
	{
		"time": 1547894583,
		"latitude": 46.751157,
		"longitude": 23.577827,
		"altitude": 474,
		"speed": 0.01,
		"timelocal": 540,
		"temperature": -2.3099999999999996,
		"pressure": 96752,
		"humidity": 88.27,
		"voc": 54443,
		"co2": 660,
		"ch2o": null,
		"pm25": null,
		"cpm": 12,
		"voltage": 377,
		"duty": 168
	},
	{
		"time": 1547894643,
		"latitude": 46.751157,
		"longitude": 23.577826,
		"altitude": 472.8,
		"speed": 0.02,
		"timelocal": 600,
		"temperature": -2.1799999999999997,
		"pressure": 96749,
		"humidity": 88.23,
		"voc": 56387,
		"co2": 657,
		"ch2o": null,
		"pm25": null,
		"cpm": 15,
		"voltage": 380,
		"duty": 169
	},
	{
		"time": 1547894703,
		"latitude": 46.751152,
		"longitude": 23.577834,
		"altitude": 472.3,
		"speed": 0.01,
		"timelocal": 660,
		"temperature": -2.0700000000000003,
		"pressure": 96745,
		"humidity": 88.18,
		"voc": 58264,
		"co2": 658,
		"ch2o": null,
		"pm25": null,
		"cpm": 10,
		"voltage": 380,
		"duty": 170
	},
	{
		"time": 1547894763,
		"latitude": 46.750867,
		"longitude": 23.577478,
		"altitude": 471.2,
		"speed": 4.26,
		"timelocal": 720,
		"temperature": -1.9699999999999998,
		"pressure": 96743,
		"humidity": 88.13,
		"voc": 60019,
		"co2": 659,
		"ch2o": null,
		"pm25": null,
		"cpm": 14,
		"voltage": 377,
		"duty": 168
	},
	{
		"time": 1547894823,
		"latitude": 46.750996,
		"longitude": 23.577288,
		"altitude": 472.3,
		"speed": 1.33,
		"timelocal": 780,
		"temperature": -1.8899999999999997,
		"pressure": 96751,
		"humidity": 88.05,
		"voc": 61411,
		"co2": 662,
		"ch2o": null,
		"pm25": null,
		"cpm": 12,
		"voltage": 380,
		"duty": 169
	},
	{
		"time": 1547894883,
		"latitude": 46.751025,
		"longitude": 23.577259,
		"altitude": 472.5,
		"speed": 0.07,
		"timelocal": 840,
		"temperature": -1.8399999999999999,
		"pressure": 96758,
		"humidity": 88,
		"voc": 63125,
		"co2": 650,
		"ch2o": null,
		"pm25": null,
		"cpm": 11,
		"voltage": 380,
		"duty": 169
	}
]