[
	{
		"time": 1538188672,
		"latitude": 46.764885,
		"longitude": 23.549157,
		"altitude": 354.1,
		"speed": 0.78,
		"timelocal": 120,
		"temperature": 8.58,
		"pressure": 97829,
		"humidity": 76.22999999999999,
		"voc": 39432,
		"co2": 606,
		"ch2o": 0,
		"pm25": 0,
		"cpm": 7,
		"voltage": 380,
		"duty": 183
	},
	{
		"time": 1538188732,
		"latitude": 46.764952,
		"longitude": 23.549333,
		"altitude": 354,
		"speed": 0.03,
		"timelocal": 180,
		"temperature": 8.9,
		"pressure": 97825,
		"humidity": 75.62,
		"voc": 41071,
		"co2": 598,
		"ch2o": 0,
		"pm25": 0,
		"cpm": 6,
		"voltage": 378,
		"duty": 183
	},
	{
		"time": 1538188792,
		"latitude": 46.764962,
		"longitude": 23.54935,
		"altitude": 353.2,
		"speed": 0.82,
		"timelocal": 240,
		"temperature": 9.11,
		"pressure": 97824,
		"humidity": 75.13,
		"voc": 42679,
		"co2": 588,
		"ch2o": 0,
		"pm25": 0,
		"cpm": 17,
		"voltage": 379,
		"duty": 183
	},
	{
		"time": 1538188852,
		"latitude": 46.765017,
		"longitude": 23.549498,
		"altitude": 352.3,
		"speed": 0.01,
		"timelocal": 300,
		"temperature": 9.29,
		"pressure": 97824,
		"humidity": 74.71000000000001,
		"voc": 45419,
		"co2": 584,
		"ch2o": 0,
		"pm25": 0,
		"cpm": 8,
		"voltage": 381,
		"duty": 185
	},
	{
		"time": 1538188912,
		"latitude": 46.765031,
		"longitude": 23.549543,
		"altitude": 353.7,
		"speed": 0.02,
		"timelocal": 360,
		"temperature": 9.45,
		"pressure": 97824,
		"humidity": 74.3,
		"voc": 48236,
		"co2": 598,
		"ch2o": 0,
		"pm25": 0,
		"cpm": 12,
		"voltage": 380,
		"duty": 185
	},
	{
		"time": 1538188972,
		"latitude": 46.765005,
		"longitude": 23.549538,
		"altitude": 352.1,
		"speed": 0.03,
		"timelocal": 420,
		"temperature": 9.600000000000001,
		"pressure": 97822,
		"humidity": 73.92,
		"voc": 50110,
		"co2": 594,
		"ch2o": 0,
		"pm25": 0,
		"cpm": 9,
		"voltage": 380,
		"duty": 185
	}
]