[
	{
		"time": 1539418208,
		"latitude": 46.78575,
		"longitude": 23.629257,
		"altitude": 320.1,
		"speed": 0.46,
		"timelocal": 120,
		"temperature": 10.879999999999999,
		"pressure": 99336,
		"humidity": 76.67,
		"voc": 98513,
		"co2": 794,
		"ch2o": 10,
		"pm25": 0,
		"cpm": 8,
		"voltage": 379,
		"duty": 187
	},
	{
		"time": 1539418268,
		"latitude": 46.78575,
		"longitude": 23.629257,
		"altitude": 320.1,
		"speed": 0.46,
		"timelocal": 180,
		"temperature": 11.3,
		"pressure": 99334,
		"humidity": 76.45,
		"voc": 95853,
		"co2": 782,
		"ch2o": 10,
		"pm25": 2,
		"cpm": 11,
		"voltage": 380,
		"duty": 187
	},
	{
		"time": 1539418328,
		"latitude": 46.78575,
		"longitude": 23.629257,
		"altitude": 320.1,
		"speed": 0.46,
		"timelocal": 240,
		"temperature": 11.579999999999998,
		"pressure": 99325,
		"humidity": 76.22,
		"voc": 96280,
		"co2": 778,
		"ch2o": 10,
		"pm25": 0,
		"cpm": 14,
		"voltage": 378,
		"duty": 187
	},
	{
		"time": 1539418387,
		"latitude": 46.78575,
		"longitude": 23.629257,
		"altitude": 320.1,
		"speed": 0.46,
		"timelocal": 300,
		"temperature": 11.84,
		"pressure": 99322,
		"humidity": 76.07,
		"voc": 97632,
		"co2": 777,
		"ch2o": 10,
		"pm25": 0,
		"cpm": 11,
		"voltage": 378,
		"duty": 187
	},
	{
		"time": 1539418447,
		"latitude": 46.78575,
		"longitude": 23.629257,
		"altitude": 320.1,
		"speed": 0.46,
		"timelocal": 360,
		"temperature": 12.079999999999998,
		"pressure": 99318,
		"humidity": 75.94,
		"voc": 98985,
		"co2": 769,
		"ch2o": 10,
		"pm25": 0,
		"cpm": 9,
		"voltage": 378,
		"duty": 187
	},
	{
		"time": 1539418507,
		"latitude": 46.78575,
		"longitude": 23.629257,
		"altitude": 320.1,
		"speed": 0.46,
		"timelocal": 420,
		"temperature": 12.329999999999998,
		"pressure": 99318,
		"humidity": 75.84,
		"voc": 99998,
		"co2": 760,
		"ch2o": 10,
		"pm25": 0,
		"cpm": 7,
		"voltage": 380,
		"duty": 189
	},
	{
		"time": 1539418567,
		"latitude": 46.78575,
		"longitude": 23.629257,
		"altitude": 320.1,
		"speed": 0.46,
		"timelocal": 480,
		"temperature": 12.57,
		"pressure": 99319,
		"humidity": 75.71000000000001,
		"voc": 101588,
		"co2": 758,
		"ch2o": 10,
		"pm25": 0,
		"cpm": 11,
		"voltage": 380,
		"duty": 189
	},
	{
		"time": 1539418627,
		"latitude": 46.78575,
		"longitude": 23.629257,
		"altitude": 320.1,
		"speed": 0.46,
		"timelocal": 540,
		"temperature": 12.8,
		"pressure": 99320,
		"humidity": 75.58,
		"voc": 102882,
		"co2": 757,
		"ch2o": 10,
		"pm25": 0,
		"cpm": 8,
		"voltage": 380,
		"duty": 189
	},
	{
		"time": 1539418687,
		"latitude": 46.78575,
		"longitude": 23.629257,
		"altitude": 320.1,
		"speed": 0.46,
		"timelocal": 600,
		"temperature": 13.030000000000001,
		"pressure": 99322,
		"humidity": 75.43,
		"voc": 103824,
		"co2": 759,
		"ch2o": 10,
		"pm25": 0,
		"cpm": 11,
		"voltage": 380,
		"duty": 189
	},
	{
		"time": 1539418747,
		"latitude": 46.78575,
		"longitude": 23.629257,
		"altitude": 320.1,
		"speed": 0.46,
		"timelocal": 660,
		"temperature": 13.25,
		"pressure": 99323,
		"humidity": 75.3,
		"voc": 104771,
		"co2": 772,
		"ch2o": 10,
		"pm25": 0,
		"cpm": 13,
		"voltage": 379,
		"duty": 189
	},
	{
		"time": 1539418807,
		"latitude": 46.78575,
		"longitude": 23.629257,
		"altitude": 320.1,
		"speed": 0.46,
		"timelocal": 720,
		"temperature": 13.46,
		"pressure": 99319,
		"humidity": 75.17,
		"voc": 105430,
		"co2": 777,
		"ch2o": 10,
		"pm25": 0,
		"cpm": 11,
		"voltage": 378,
		"duty": 189
	},
	{
		"time": 1539418867,
		"latitude": 46.78575,
		"longitude": 23.629257,
		"altitude": 320.1,
		"speed": 0.46,
		"timelocal": 780,
		"temperature": 13.66,
		"pressure": 99322,
		"humidity": 75,
		"voc": 106070,
		"co2": 788,
		"ch2o": 10,
		"pm25": 0,
		"cpm": 7,
		"voltage": 378,
		"duty": 189
	},
	{
		"time": 1539418927,
		"latitude": 46.78575,
		"longitude": 23.629257,
		"altitude": 320.1,
		"speed": 0.46,
		"timelocal": 840,
		"temperature": 13.809999999999999,
		"pressure": 99317,
		"humidity": 74.77000000000001,
		"voc": 106887,
		"co2": 794,
		"ch2o": 10,
		"pm25": 0,
		"cpm": 4,
		"voltage": 378,
		"duty": 189
	}
]